word_generator/__init__.py
random_english_word_generator-1.0.1.dist-info/METADATA
random_english_word_generator-1.0.1.dist-info/WHEEL
random_english_word_generator-1.0.1.dist-info/top_level.txt
random_english_word_generator-1.0.1.dist-info/RECORD
