Metadata-Version: 2.1
Name: random-english-word-generator
Version: 1.0.1
Summary: A Python package to generate random English words based on word length and count
Home-page: 
Author: Random Generator AI
Author-email: randomgenerate.ai@gmail.com
Classifier: Programming Language :: Python :: 3
Classifier: License :: OSI Approved :: MIT License
Classifier: Operating System :: OS Independent
Requires-Python: >=3.6
Requires-Dist: nltk
